ank/__init__.py
ank/chain_process.py
ank/cli.py
ank/daemon.py
ank/generate_processor.py
ank/generate_setting.py
ank/head_process.py
ank/apps/__init__.py
ank/apps/api_app.py
ank/apps/join_app.py
ank/apps/kafka_consumer.py
ank/apps/kafka_producer.py
ank/apps/log_app.py
ank/apps/pipe_app.py
ank/apps/rabbitmq_consumer.py
ank/apps/rabbitmq_producer.py
ank/apps/redis_subscribe.py
ank/apps/schedule_app.py
ank/apps/split_app.py
ank/apps/zmq_consumer.py
ank/apps/zmq_producer.py
ank/base_apps/__init__.py
ank/base_apps/api_app.py
ank/base_apps/pipe_app.py
ank/base_apps/schedule_app.py
ank/deploy/__init__.py
ank/deploy/chain_processor.py
ank/deploy/daemon.py
ank/deploy/dependency_injection.py
ank/deploy/generate_processor.py
ank/deploy/generate_setting.py
ank/templates/__init__.py
ank/tests/__init__.py
ank/tests/processor.py
ank/tests/test_deploy.py
ank/utils/__init__.py
ank/utils/api_helpers.py
ank/utils/cmd_helpers.py
ank/utils/config_handle.py
ank/utils/crontab_time.py
ank/utils/logger.py
ank/utils/naming_services.py
ank-1.5.5.dist-info/METADATA
ank-1.5.5.dist-info/RECORD
ank-1.5.5.dist-info/WHEEL
ank-1.5.5.dist-info/entry_points.txt
ank-1.5.5.dist-info/top_level.txt
apps/__init__.py
apps/join_app.py
apps/kafka_consumer.py
apps/kafka_producer.py
apps/log_app.py
apps/rabbitmq_consumer.py
apps/rabbitmq_producer.py
apps/redis_subscribe.py
apps/split_app.py
apps/zmq_consumer.py
apps/zmq_producer.py
base_apps/__init__.py
base_apps/api_app.py
base_apps/pipe_app.py
base_apps/schedule_app.py
deploy/__init__.py
deploy/chain_processor.py
deploy/daemon.py
deploy/dependency_injection.py
deploy/generate_processor.py
deploy/generate_setting.py
examples/api_app/__init__.py
examples/api_app/endpoint.py
examples/api_app/processor.py
examples/schedule_app/__init__.py
examples/schedule_app/processor.py
examples/streaming_app/__init__.py
examples/streaming_app/processor.py
templates/__init__.py
templates/apiapp_endpoint.tpy
templates/apiapp_processor.tpy
templates/apiapp_services.tpy
templates/apiapp_settings.tpy
templates/baseapp_processor.tpy
