Metadata-Version: 2.1
Name: ank
Version: 1.5.5
Summary: Python Streaming system, REST-API and Schedule task using queue message
Home-page: https://github.com/sunary/ank
Author: Sunary [Nhat Vo Van]
Author-email: v2nhat@gmail.com
License: All code is released under the MIT License:
Requires-Dist: pyyaml (==3.12)
Requires-Dist: flask (==1.0.2)
Requires-Dist: redis (==2.10.5)
Requires-Dist: pika (==0.10.0)
Requires-Dist: pyzmq (==16.0.2)
Requires-Dist: kafka-python (==0.9.5)
